{
  "id": "22435c587ebc44f3acc1742532d8bee8",
  "namespace": "ue",
  "title": "[AMB] A Library",
  "description": "A Library",
  "longDescription": "<p>A collection of Library assets and a demo &#34;victorian&#34; library setup . asset contains blueprints made to ease the level building prosess,</p><p><br /></p><p>Take A Look At</p><p><br /></p><ul><li><a href=\"https://www.unrealengine.com/marketplace/en-US/product/aui\" rel=\"nofollow\">AUI</a> - <a href=\"https://www.youtube.com/watch?v&#61;2ey4iMCgwuU\" rel=\"nofollow\">Trailer</a></li><li><a href=\"https://www.unrealengine.com/marketplace/en-US/product/a-bottle-pack\" rel=\"nofollow\">A Bottle Pack</a></li><li><a href=\"https://www.unrealengine.com/marketplace/en-US/product/a-gem-pack\" rel=\"nofollow\">A Gem Pack</a></li><li><a href=\"https://www.unrealengine.com/marketplace/en-US/product/a-board-game\" rel=\"nofollow\">A Board Game</a></li><li><a href=\"https://www.unrealengine.com/marketplace/en-US/product/a-library\" rel=\"nofollow\">A Library</a> - <a href=\"https://www.youtube.com/watch?v&#61;h31njfLB5mc\" rel=\"nofollow\">Trailer</a></li><li><a href=\"https://www.unrealengine.com/marketplace/en-US/product/a-jukebox\" rel=\"nofollow\">A JukeBox</a> - <a href=\"https://www.youtube.com/watch?v&#61;KnhXy6rFfgc\" rel=\"nofollow\">Trailer</a></li><li><a href=\"https://www.unrealengine.com/marketplace/en-US/product/a-card-game\" rel=\"nofollow\">A Card Game</a> - <a href=\"https://www.youtube.com/watch?v&#61;oNua5Rfnd6Q\" rel=\"nofollow\">Trailer</a></li><li><a href=\"https://www.unrealengine.com/marketplace/en-US/product/amb-a-book-generator\" rel=\"nofollow\">A Book Generator</a></li><li><a href=\"https://www.unrealengine.com/marketplace/en-US/product/a-fishing-system\" rel=\"nofollow\">A Fish System</a> - <a href=\"https://www.youtube.com/watch?v&#61;DCLDaO-7GUg\" rel=\"nofollow\">Trailer</a></li><li><a href=\"https://www.unrealengine.com/marketplace/en-US/product/amb-a-fast-travel\" rel=\"nofollow\">A Fast Travel System</a></li><li><a href=\"https://www.unrealengine.com/marketplace/en-US/product/a-ocean\" rel=\"nofollow\">A Ocean</a></li></ul><p><br /></p><p>Support <a href=\"https://discord.gg/YtBwNYJT\" rel=\"nofollow\">Discord</a></p>",
  "status": "ACTIVE",
  "productSlug": null,
  "urlSlug": "a-library",
  "creationDate": "2023-11-20T16:23:39.496Z",
  "lastModifiedDate": "2024-11-03T11:20:19.519Z",
  "effectiveDate": "2023-11-20T16:23:39.416Z",
  "viewableDate": null,
  "developer": null,
  "seller": {
    "id": "o-9jbgr3ee5lu9pcfx7snt8q34cf5cpv",
    "name": "AMB Studios"
  },
  "linkedOfferId": null,
  "isFeatured": false,
  "ignoreOrder": false,
  "freeDays": 0,
  "collectionOfferIds": [],
  "technicalDetails": "<p>Features:</p><p><br /></p><ul><li> Modular Building Modules</li></ul><p><em>\tWall, Floor, Roof, Pillars, Arch, Windows, Wall Door, Wall Window, Stairs</em></p><ul><li>BP Book <em>Randomizer</em></li><li>BP Scroll <em>Randomizer</em></li><li>BP Book Spline <em>Randomizer</em></li><li>BP Book Spline Series</li><li>BP Book Shelf Randomizer</li><li>BP Book Shelf <em>Randomizer</em> Array</li><li>BP Reading Table Prop <em>Randomizer</em>, Interactable Light</li><li>BP Picture <em>Randomizer</em> Art, Frame, Lamp , Interactable Light</li><li>BP BoardGame <em>Randomizer</em></li><li>BP Planetarium Galaxy Spinning rings Prop</li><li>BP Planetarium Ring Spinning</li><li>BP planetarium Planetarium</li><li>BP Door <em>Interactable</em> Open &amp; Close</li><li>BP Window <em>Interactable</em> Open &amp; Close</li><li>BP Table Lamp <em>Interactable</em> On Off</li><li>BP Wall Lamp <em>Interactable</em> On &amp; Off</li><li>BP Showcase <em>Interactable</em> Open &amp; Close</li><li>Seamless wood texture and normal 3456*3456</li></ul><p><br /></p><p>Number of Unique Meshes: 80&#43;</p><p>Numbers of Blueprints 17</p><p>Numbers Of Maps 2, Library enviorment and overview</p><p>Collision: (Yes/custom)</p><p>LODs: (No)</p><p>Number of Materials and Material Instances: 50 &#34;note some is just pure solid but set for the option to customize</p><p>Number of Textures:22</p><p>Supported Development Platforms:</p><p>Windows: (Yes)</p><p>Documentation: Link (or a description of where users can find) the documentation</p><p>Important/Additional Notes: Doors and windows can only open and close when in game or simlulate game. alll interactables have a interact function and a button in the details panel, if any good ideas for models ill create em on the go and update asset.</p>",
  "recurrence": "ONCE",
  "categories": [
    {
      "path": "assets"
    },
    {
      "path": "assets/environments"
    }
  ],
  "tags": [
    {
      "id": null,
      "name": null,
      "namespace": null,
      "aliases": null,
      "operator": null,
      "created": null,
      "updated": null,
      "status": null,
      "referenceCount": null,
      "comment": null
    },
    {
      "id": null,
      "name": null,
      "namespace": null,
      "aliases": null,
      "operator": null,
      "created": null,
      "updated": null,
      "status": null,
      "referenceCount": null,
      "comment": null
    },
    {
      "id": null,
      "name": null,
      "namespace": null,
      "aliases": null,
      "operator": null,
      "created": null,
      "updated": null,
      "status": null,
      "referenceCount": null,
      "comment": null
    },
    {
      "id": null,
      "name": null,
      "namespace": null,
      "aliases": null,
      "operator": null,
      "created": null,
      "updated": null,
      "status": null,
      "referenceCount": null,
      "comment": null
    },
    {
      "id": null,
      "name": null,
      "namespace": null,
      "aliases": null,
      "operator": null,
      "created": null,
      "updated": null,
      "status": null,
      "referenceCount": null,
      "comment": null
    },
    {
      "id": null,
      "name": null,
      "namespace": null,
      "aliases": null,
      "operator": null,
      "created": null,
      "updated": null,
      "status": null,
      "referenceCount": null,
      "comment": null
    },
    {
      "id": null,
      "name": null,
      "namespace": null,
      "aliases": null,
      "operator": null,
      "created": null,
      "updated": null,
      "status": null,
      "referenceCount": null,
      "comment": null
    },
    {
      "id": null,
      "name": null,
      "namespace": null,
      "aliases": null,
      "operator": null,
      "created": null,
      "updated": null,
      "status": null,
      "referenceCount": null,
      "comment": null
    },
    {
      "id": null,
      "name": null,
      "namespace": null,
      "aliases": null,
      "operator": null,
      "created": null,
      "updated": null,
      "status": null,
      "referenceCount": null,
      "comment": null
    },
    {
      "id": null,
      "name": null,
      "namespace": null,
      "aliases": null,
      "operator": null,
      "created": null,
      "updated": null,
      "status": null,
      "referenceCount": null,
      "comment": null
    },
    {
      "id": null,
      "name": null,
      "namespace": null,
      "aliases": null,
      "operator": null,
      "created": null,
      "updated": null,
      "status": null,
      "referenceCount": null,
      "comment": null
    },
    {
      "id": null,
      "name": null,
      "namespace": null,
      "aliases": null,
      "operator": null,
      "created": null,
      "updated": null,
      "status": null,
      "referenceCount": null,
      "comment": null
    },
    {
      "id": null,
      "name": null,
      "namespace": null,
      "aliases": null,
      "operator": null,
      "created": null,
      "updated": null,
      "status": null,
      "referenceCount": null,
      "comment": null
    },
    {
      "id": null,
      "name": null,
      "namespace": null,
      "aliases": null,
      "operator": null,
      "created": null,
      "updated": null,
      "status": null,
      "referenceCount": null,
      "comment": null
    },
    {
      "id": null,
      "name": null,
      "namespace": null,
      "aliases": null,
      "operator": null,
      "created": null,
      "updated": null,
      "status": null,
      "referenceCount": null,
      "comment": null
    },
    {
      "id": null,
      "name": null,
      "namespace": null,
      "aliases": null,
      "operator": null,
      "created": null,
      "updated": null,
      "status": null,
      "referenceCount": null,
      "comment": null
    }
  ],
  "customAttributes": [
    {
      "key": "FabListingId",
      "value": "17230832-5d1d-4fbe-b787-490e002358e6"
    }
  ],
  "keyImages": [
    {
      "type": "Screenshot",
      "url": "https://cdn1.epicgames.com/ue/product/Screenshot/22-1920x1080-268d36c85d77c379ead2f23ec89afb4c.png",
      "md5": "268d36c85d77c379ead2f23ec89afb4c",
      "size": 2792446,
      "uploadedDate": "2023-11-18T09:20:28.805Z",
      "width": 1920,
      "height": 1080
    },
    {
      "type": "Screenshot",
      "url": "https://cdn1.epicgames.com/ue/product/Screenshot/23-1920x1080-6b7c6f226d1f449565464ab812c977a3.png",
      "md5": "6b7c6f226d1f449565464ab812c977a3",
      "size": 2391863,
      "uploadedDate": "2023-11-18T09:20:29.418Z",
      "width": 1920,
      "height": 1080
    },
    {
      "type": "Screenshot",
      "url": "https://cdn1.epicgames.com/ue/product/Screenshot/29-1920x1080-dfa1325773a1f3873ea660a3f326415e.png",
      "md5": "dfa1325773a1f3873ea660a3f326415e",
      "size": 2200605,
      "uploadedDate": "2023-11-18T09:20:29.966Z",
      "width": 1920,
      "height": 1080
    },
    {
      "type": "Screenshot",
      "url": "https://cdn1.epicgames.com/ue/product/Screenshot/25-1920x1080-48755d5f00d9d77b211ba7282492b2cd.png",
      "md5": "48755d5f00d9d77b211ba7282492b2cd",
      "size": 2751717,
      "uploadedDate": "2023-11-18T09:20:30.516Z",
      "width": 1920,
      "height": 1080
    },
    {
      "type": "Screenshot",
      "url": "https://cdn1.epicgames.com/ue/product/Screenshot/31-1920x1080-f2720da93d5cdc700e54f70c2332f845.png",
      "md5": "f2720da93d5cdc700e54f70c2332f845",
      "size": 2136651,
      "uploadedDate": "2023-11-18T09:20:31.135Z",
      "width": 1920,
      "height": 1080
    },
    {
      "type": "Screenshot",
      "url": "https://cdn1.epicgames.com/ue/product/Screenshot/27-1920x1080-dc8f80ba8a0c889541047010904e4317.png",
      "md5": "dc8f80ba8a0c889541047010904e4317",
      "size": 1937734,
      "uploadedDate": "2023-11-18T09:20:31.754Z",
      "width": 1920,
      "height": 1080
    },
    {
      "type": "Screenshot",
      "url": "https://cdn1.epicgames.com/ue/product/Screenshot/11-1920x1080-3bd5a949a58dfa17b1977c6ea1c49333.png",
      "md5": "3bd5a949a58dfa17b1977c6ea1c49333",
      "size": 1971053,
      "uploadedDate": "2023-11-18T09:20:32.337Z",
      "width": 1920,
      "height": 1080
    },
    {
      "type": "Screenshot",
      "url": "https://cdn1.epicgames.com/ue/product/Screenshot/18-1920x1080-a490af3192278c0a46e2bdfcb9e125c7.png",
      "md5": "a490af3192278c0a46e2bdfcb9e125c7",
      "size": 2456227,
      "uploadedDate": "2023-11-18T09:20:32.909Z",
      "width": 1920,
      "height": 1080
    },
    {
      "type": "Screenshot",
      "url": "https://cdn1.epicgames.com/ue/product/Screenshot/14-1920x1080-ed37bb1a39a16735e65738360aabfe2c.png",
      "md5": "ed37bb1a39a16735e65738360aabfe2c",
      "size": 2575571,
      "uploadedDate": "2023-11-18T09:20:33.482Z",
      "width": 1920,
      "height": 1080
    },
    {
      "type": "Screenshot",
      "url": "https://cdn1.epicgames.com/ue/product/Screenshot/13-1920x1080-4efbc0c07c46dcf10e144ad373ceefb6.png",
      "md5": "4efbc0c07c46dcf10e144ad373ceefb6",
      "size": 2438047,
      "uploadedDate": "2023-11-18T09:20:34.092Z",
      "width": 1920,
      "height": 1080
    },
    {
      "type": "Screenshot",
      "url": "https://cdn1.epicgames.com/ue/product/Screenshot/19-1920x1080-02e66a45ba39c01001bafa2ee10868b2.png",
      "md5": "02e66a45ba39c01001bafa2ee10868b2",
      "size": 1986376,
      "uploadedDate": "2023-11-18T09:20:34.692Z",
      "width": 1920,
      "height": 1080
    },
    {
      "type": "Thumbnail",
      "url": "https://cdn1.epicgames.com/ue/product/Thumbnail/ALibrary_thumb-284x284-487234d327d658cadc3d4188277c0fd0.png",
      "md5": "487234d327d658cadc3d4188277c0fd0",
      "size": 165081,
      "uploadedDate": "2023-11-18T09:20:35.100Z",
      "width": 284,
      "height": 284
    },
    {
      "type": "Featured",
      "url": "https://cdn1.epicgames.com/ue/product/Featured/ALibrary_featured-894x488-27397d95691bb526e93e80ba225dfef2.png",
      "md5": "27397d95691bb526e93e80ba225dfef2",
      "size": 719308,
      "uploadedDate": "2023-11-18T09:20:35.228Z",
      "width": 894,
      "height": 488
    },
    {
      "type": "Snapshot",
      "url": "https://cdn1.epicgames.com/ue/product/Snapshot/22-1920x1080-268d36c85d77c379ead2f23ec89afb4c_Snapshot.png",
      "md5": "bd28566c58dfc037d890db0b8a086c2b",
      "size": 8543,
      "uploadedDate": "2023-11-18T09:20:29.202Z",
      "width": 150,
      "height": 74
    },
    {
      "type": "Snapshot",
      "url": "https://cdn1.epicgames.com/ue/product/Snapshot/23-1920x1080-6b7c6f226d1f449565464ab812c977a3_Snapshot.png",
      "md5": "cade4f0a2851294956baae08858ebfe6",
      "size": 7173,
      "uploadedDate": "2023-11-18T09:20:29.758Z",
      "width": 150,
      "height": 74
    },
    {
      "type": "Snapshot",
      "url": "https://cdn1.epicgames.com/ue/product/Snapshot/29-1920x1080-dfa1325773a1f3873ea660a3f326415e_Snapshot.png",
      "md5": "1bb6457b347f2e87f15823c54c4c23fd",
      "size": 5524,
      "uploadedDate": "2023-11-18T09:20:30.269Z",
      "width": 150,
      "height": 74
    },
    {
      "type": "Snapshot",
      "url": "https://cdn1.epicgames.com/ue/product/Snapshot/25-1920x1080-48755d5f00d9d77b211ba7282492b2cd_Snapshot.png",
      "md5": "b1c093cae471d669b0c7b95753275a92",
      "size": 8439,
      "uploadedDate": "2023-11-18T09:20:30.930Z",
      "width": 150,
      "height": 74
    },
    {
      "type": "Snapshot",
      "url": "https://cdn1.epicgames.com/ue/product/Snapshot/31-1920x1080-f2720da93d5cdc700e54f70c2332f845_Snapshot.png",
      "md5": "b4daa587efb61ab7f27f6bddccbb3d60",
      "size": 7052,
      "uploadedDate": "2023-11-18T09:20:31.495Z",
      "width": 150,
      "height": 74
    },
    {
      "type": "Snapshot",
      "url": "https://cdn1.epicgames.com/ue/product/Snapshot/27-1920x1080-dc8f80ba8a0c889541047010904e4317_Snapshot.png",
      "md5": "ad9e4f6df67438d0e7131ff95903ac62",
      "size": 5797,
      "uploadedDate": "2023-11-18T09:20:32.076Z",
      "width": 150,
      "height": 74
    },
    {
      "type": "Snapshot",
      "url": "https://cdn1.epicgames.com/ue/product/Snapshot/11-1920x1080-3bd5a949a58dfa17b1977c6ea1c49333_Snapshot.png",
      "md5": "e53798ad4d3b10e9ea77450b965ac04d",
      "size": 5806,
      "uploadedDate": "2023-11-18T09:20:32.634Z",
      "width": 150,
      "height": 74
    },
    {
      "type": "Snapshot",
      "url": "https://cdn1.epicgames.com/ue/product/Snapshot/18-1920x1080-a490af3192278c0a46e2bdfcb9e125c7_Snapshot.png",
      "md5": "c7f1171140471e590994f3d262fb80f6",
      "size": 7949,
      "uploadedDate": "2023-11-18T09:20:33.272Z",
      "width": 150,
      "height": 74
    },
    {
      "type": "Snapshot",
      "url": "https://cdn1.epicgames.com/ue/product/Snapshot/14-1920x1080-ed37bb1a39a16735e65738360aabfe2c_Snapshot.png",
      "md5": "d048d741a83e136a906ba54390b2f6a6",
      "size": 7487,
      "uploadedDate": "2023-11-18T09:20:33.785Z",
      "width": 150,
      "height": 74
    },
    {
      "type": "Snapshot",
      "url": "https://cdn1.epicgames.com/ue/product/Snapshot/13-1920x1080-4efbc0c07c46dcf10e144ad373ceefb6_Snapshot.png",
      "md5": "9b286df07da3fca151f8d0d049397abe",
      "size": 7327,
      "uploadedDate": "2023-11-18T09:20:34.482Z",
      "width": 150,
      "height": 74
    },
    {
      "type": "Snapshot",
      "url": "https://cdn1.epicgames.com/ue/product/Snapshot/19-1920x1080-02e66a45ba39c01001bafa2ee10868b2_Snapshot.png",
      "md5": "137c5e276e05f6b7c3093ec0e9842b53",
      "size": 5881,
      "uploadedDate": "2023-11-18T09:20:34.973Z",
      "width": 150,
      "height": 74
    }
  ],
  "items": [
    {
      "id": "3ad6ad2238f346388f6df153de198933"
    }
  ],
  "catalogNs": null
}