{
  "id": "22e877cedaed4cc5881c7ab4d1951fd2",
  "namespace": "4cbd830175c6402e98ef67421c0c1bec",
  "title": "2,000 Crystals",
  "description": "Buy 2,000 Death Blonde Crystals, the in-game currency that can be spent in Death Blonde. Use them to unlock exclusive customization items in the shop, purchase special loot boxes, join powerful factions, or grab the latest season pass for even more content!",
  "longDescription": "<!--textBlock-->\n<!--title-->\n# Amazing premium cash\n<!--text-->\nBoost your death experience into J-city\n",
  "status": "ACTIVE",
  "productSlug": null,
  "urlSlug": "premium-cash-2000",
  "creationDate": "2024-02-19T21:59:09.464Z",
  "lastModifiedDate": "2024-10-29T05:37:32.045Z",
  "effectiveDate": "2099-01-01T00:00:00.000Z",
  "viewableDate": "2024-07-17T11:00:01.555Z",
  "developer": null,
  "seller": {
    "id": "o-64lqtczdx3w4tenyzcwqgh36ndw3ks",
    "name": "Demon Girl"
  },
  "linkedOfferId": null,
  "isFeatured": false,
  "ignoreOrder": false,
  "freeDays": 0,
  "collectionOfferIds": [],
  "technicalDetails": null,
  "recurrence": "ONCE",
  "categories": [
    {
      "path": "spthidden/consumable"
    },
    {
      "path": "spthidden"
    }
  ],
  "tags": [
    {
      "id": "9547",
      "name": "Windows",
      "namespace": "epic",
      "aliases": [],
      "operator": null,
      "created": "2019-10-11T02:43:18.435Z",
      "updated": "2023-08-23T05:17:12.978Z",
      "status": "ACTIVE",
      "referenceCount": 16447,
      "comment": null
    },
    {
      "id": "10719",
      "name": "Mac OS",
      "namespace": "epic",
      "aliases": [
        "OSX",
        "macOS"
      ],
      "operator": null,
      "created": "2019-10-11T02:43:27.812Z",
      "updated": "2023-08-23T05:08:24.605Z",
      "status": "ACTIVE",
      "referenceCount": 1308,
      "comment": null
    }
  ],
  "customAttributes": [
    {
      "key": "autoGeneratedPrice",
      "value": "false"
    },
    {
      "key": "isManuallySetViewableDate",
      "value": "true"
    },
    {
      "key": "isPromotionalContentUsed",
      "value": "null"
    },
    {
      "key": "isManuallySetPCReleaseDate",
      "value": "false"
    },
    {
      "key": "isBlockchainUsed",
      "value": "false"
    }
  ],
  "keyImages": [
    {
      "type": "OfferImageWide",
      "url": "https://cdn1.epicgames.com/spt-assets/8a8f659c6ede4b8b92335d6d36eac298/death-blonde-1jbqm.png",
      "md5": "bc8f9eb831bd9289ab747634a2288f1c",
      "size": 2137627,
      "uploadedDate": "2024-07-16T17:39:50.370Z",
      "width": 2560,
      "height": 1440
    },
    {
      "type": "OfferImageTall",
      "url": "https://cdn1.epicgames.com/spt-assets/8a8f659c6ede4b8b92335d6d36eac298/death-blonde-4a907.jpeg",
      "md5": "8d8edf818e5b8730f08671d6d4333d30",
      "size": 190767,
      "uploadedDate": "2024-02-19T22:08:03.058Z",
      "width": 1200,
      "height": 1600
    },
    {
      "type": "Thumbnail",
      "url": "https://cdn1.epicgames.com/spt-assets/8a8f659c6ede4b8b92335d6d36eac298/death-blonde-4a907.jpeg",
      "md5": "8d8edf818e5b8730f08671d6d4333d30",
      "size": 190767,
      "uploadedDate": "2024-02-19T22:08:03.058Z",
      "width": 1200,
      "height": 1600
    },
    {
      "type": "featuredMedia",
      "url": "https://cdn1.epicgames.com/spt-assets/8a8f659c6ede4b8b92335d6d36eac298/death-blonde-sbo6x.png",
      "md5": "098f6bcd4621d373cade4e832627b4f6",
      "size": 1403835,
      "uploadedDate": "2024-07-16T18:46:34.383Z",
      "width": 1920,
      "height": 1080
    }
  ],
  "items": [
    {
      "id": "565b8aa709714fde91d36dc103f155b3"
    }
  ],
  "catalogNs": {
    "name": "4cbd830175c6402e98ef67421c0c1bec"
  }
}