{
  "id": "c6b532fccb0f40f4839cd883e07e017a",
  "namespace": "9df0882d086e4c6c97d720c796675ab3",
  "title": "Dolphin Spirit - Ocean Mission",
  "description": "Embark on an amazing adventure on the tropical island of Maupiroa! Take to the seas and discover the secrets that surround the island!  Dive into the ocean's depths, teeming with life and color, with your dolphin friend Keanu.",
  "longDescription": null,
  "status": "ACTIVE",
  "productSlug": null,
  "urlSlug": "11787e0961b646fe97deb616be007442",
  "creationDate": "2023-04-17T15:00:18.572Z",
  "lastModifiedDate": "2023-04-17T15:00:18.572Z",
  "effectiveDate": "2099-01-01T00:00:00.000Z",
  "viewableDate": "2023-04-05T13:00:00.000Z",
  "developer": null,
  "seller": {
    "id": "o-lyvtyhgthgebq7jdg4wu6km9lyjp2h",
    "name": "Microids"
  },
  "linkedOfferId": null,
  "isFeatured": false,
  "ignoreOrder": false,
  "freeDays": 0,
  "collectionOfferIds": [],
  "technicalDetails": null,
  "recurrence": "ONCE",
  "categories": [
    {
      "path": "games/edition/base"
    },
    {
      "path": "games/edition"
    },
    {
      "path": "games"
    }
  ],
  "tags": [
    null,
    null,
    null
  ],
  "customAttributes": [
    {
      "key": "autoGeneratedPrice",
      "value": "false"
    },
    {
      "key": "isManuallySetViewableDate",
      "value": "true"
    },
    {
      "key": "isManuallySetPCReleaseDate",
      "value": "false"
    },
    {
      "key": "isBlockchainUsed",
      "value": "false"
    }
  ],
  "keyImages": [
    {
      "type": "OfferImageWide",
      "url": "https://cdn1.epicgames.com/spt-assets/dc945fa01cf1479fbe6d5e1f96219a99/dolphin-spirit--ocean-mission-1ic5f.jpg",
      "md5": "a55b114aa4537e0be87481850ec7a4a6",
      "size": 2740623,
      "uploadedDate": "2023-04-05T13:11:50.013Z",
      "width": 2560,
      "height": 1440
    },
    {
      "type": "OfferImageTall",
      "url": "https://cdn1.epicgames.com/spt-assets/dc945fa01cf1479fbe6d5e1f96219a99/dolphin-spirit--ocean-mission-bhuxd.jpg",
      "md5": "a55c13b647533349326caed1f032d71c",
      "size": 1447346,
      "uploadedDate": "2023-04-05T13:11:54.009Z",
      "width": 1200,
      "height": 1600
    },
    {
      "type": "Thumbnail",
      "url": "https://cdn1.epicgames.com/spt-assets/dc945fa01cf1479fbe6d5e1f96219a99/dolphin-spirit--ocean-mission-bhuxd.jpg",
      "md5": "a55c13b647533349326caed1f032d71c",
      "size": 1447346,
      "uploadedDate": "2023-04-05T13:11:54.009Z",
      "width": 1200,
      "height": 1600
    }
  ],
  "items": [
    {
      "id": "8e120a3fc2274709b3401f908ea0a770"
    }
  ],
  "catalogNs": {
    "name": "9df0882d086e4c6c97d720c796675ab3"
  }
}