{
  "id": "d9f9524561b94719b80760de28453f12",
  "namespace": "ue",
  "title": "BACKGROUND - Cartoon Garden 2",
  "description": "Cartoon art style garden background environments.",
  "longDescription": "<p>This pack contains 6 cartoon art style garden background environment locations:</p><ul><li>Fountain Courtyard</li><li>Mushroom Garden</li><li>Serenity Pond</li><li>Sunflower Field</li><li>Tulip Garden</li><li>Windmill Garden</li></ul><p><br /></p><p>Perfect for Visual Novel Backgrounds, Character Backgrounds, Themed Backgrounds, Storytelling, Store Listing, Location Highlighting, Board Games, RPG Games, Adventure Games, Main Theme, Loading Page, Dialogue Page, TCG, UI, etc... Feel free to use them in any way you like.</p>",
  "status": "ACTIVE",
  "productSlug": null,
  "urlSlug": "background-cartoon-garden-2",
  "creationDate": "2024-01-13T07:58:43.952Z",
  "lastModifiedDate": "2024-10-05T12:26:51.953Z",
  "effectiveDate": "2024-01-13T07:58:43.907Z",
  "viewableDate": null,
  "developer": null,
  "seller": {
    "id": "o-5nbp8svkqzv3gsjrablrgza2tz6h2p",
    "name": "Dreamly Studios"
  },
  "linkedOfferId": null,
  "isFeatured": false,
  "ignoreOrder": false,
  "freeDays": 0,
  "collectionOfferIds": [],
  "technicalDetails": "<p>Features:</p><ul><li>6 Environment locations</li><li>60 cartoon art style backgrounds</li><li>PNG images</li><li>3840x2160 pixels size </li></ul><p> </p><p>Number of Textures: 60</p><p>Texture Resolutions: 3840x2160</p><p>Supported Development Platforms:</p><p>Windows: Yes</p><p>Mac: Yes</p><p>AI Software: Midjourney</p>",
  "recurrence": "ONCE",
  "categories": [
    {
      "path": "assets/2d"
    },
    {
      "path": "assets"
    }
  ],
  "tags": [
    {
      "id": null,
      "name": null,
      "namespace": null,
      "aliases": null,
      "operator": null,
      "created": null,
      "updated": null,
      "status": null,
      "referenceCount": null,
      "comment": null
    },
    {
      "id": null,
      "name": null,
      "namespace": null,
      "aliases": null,
      "operator": null,
      "created": null,
      "updated": null,
      "status": null,
      "referenceCount": null,
      "comment": null
    },
    {
      "id": null,
      "name": null,
      "namespace": null,
      "aliases": null,
      "operator": null,
      "created": null,
      "updated": null,
      "status": null,
      "referenceCount": null,
      "comment": null
    },
    {
      "id": null,
      "name": null,
      "namespace": null,
      "aliases": null,
      "operator": null,
      "created": null,
      "updated": null,
      "status": null,
      "referenceCount": null,
      "comment": null
    },
    {
      "id": null,
      "name": null,
      "namespace": null,
      "aliases": null,
      "operator": null,
      "created": null,
      "updated": null,
      "status": null,
      "referenceCount": null,
      "comment": null
    },
    {
      "id": null,
      "name": null,
      "namespace": null,
      "aliases": null,
      "operator": null,
      "created": null,
      "updated": null,
      "status": null,
      "referenceCount": null,
      "comment": null
    },
    {
      "id": null,
      "name": null,
      "namespace": null,
      "aliases": null,
      "operator": null,
      "created": null,
      "updated": null,
      "status": null,
      "referenceCount": null,
      "comment": null
    },
    {
      "id": null,
      "name": null,
      "namespace": null,
      "aliases": null,
      "operator": null,
      "created": null,
      "updated": null,
      "status": null,
      "referenceCount": null,
      "comment": null
    },
    {
      "id": null,
      "name": null,
      "namespace": null,
      "aliases": null,
      "operator": null,
      "created": null,
      "updated": null,
      "status": null,
      "referenceCount": null,
      "comment": null
    },
    {
      "id": null,
      "name": null,
      "namespace": null,
      "aliases": null,
      "operator": null,
      "created": null,
      "updated": null,
      "status": null,
      "referenceCount": null,
      "comment": null
    },
    {
      "id": null,
      "name": null,
      "namespace": null,
      "aliases": null,
      "operator": null,
      "created": null,
      "updated": null,
      "status": null,
      "referenceCount": null,
      "comment": null
    },
    {
      "id": null,
      "name": null,
      "namespace": null,
      "aliases": null,
      "operator": null,
      "created": null,
      "updated": null,
      "status": null,
      "referenceCount": null,
      "comment": null
    },
    {
      "id": null,
      "name": null,
      "namespace": null,
      "aliases": null,
      "operator": null,
      "created": null,
      "updated": null,
      "status": null,
      "referenceCount": null,
      "comment": null
    },
    {
      "id": null,
      "name": null,
      "namespace": null,
      "aliases": null,
      "operator": null,
      "created": null,
      "updated": null,
      "status": null,
      "referenceCount": null,
      "comment": null
    },
    {
      "id": null,
      "name": null,
      "namespace": null,
      "aliases": null,
      "operator": null,
      "created": null,
      "updated": null,
      "status": null,
      "referenceCount": null,
      "comment": null
    }
  ],
  "customAttributes": [
    {
      "key": "FabListingId",
      "value": "cca59783-072c-401a-8090-36e8fdbc77e5"
    }
  ],
  "keyImages": [
    {
      "type": "Screenshot",
      "url": "https://cdn1.epicgames.com/ue/product/Screenshot/Screenshot0-1920x1080-0fc545616e34c64cc4d32f6fa812ca2c.jpg",
      "md5": "0fc545616e34c64cc4d32f6fa812ca2c",
      "size": 982444,
      "uploadedDate": "2024-01-09T15:16:20.899Z",
      "width": 1920,
      "height": 1080
    },
    {
      "type": "Screenshot",
      "url": "https://cdn1.epicgames.com/ue/product/Screenshot/Screenshot01-1920x1080-c125a078b977301085953cd9d3296a1c.jpg",
      "md5": "c125a078b977301085953cd9d3296a1c",
      "size": 453408,
      "uploadedDate": "2024-01-09T15:16:21.538Z",
      "width": 1920,
      "height": 1080
    },
    {
      "type": "Screenshot",
      "url": "https://cdn1.epicgames.com/ue/product/Screenshot/Screenshot02-1920x1080-7a57ba32cafa5ef2ec18e09980a94f4a.jpg",
      "md5": "7a57ba32cafa5ef2ec18e09980a94f4a",
      "size": 526450,
      "uploadedDate": "2024-01-09T15:16:22.170Z",
      "width": 1920,
      "height": 1080
    },
    {
      "type": "Screenshot",
      "url": "https://cdn1.epicgames.com/ue/product/Screenshot/Screenshot03-1920x1080-4e26cff8524d5b3a9c347bf119344af1.jpg",
      "md5": "4e26cff8524d5b3a9c347bf119344af1",
      "size": 435008,
      "uploadedDate": "2024-01-09T15:16:22.838Z",
      "width": 1920,
      "height": 1080
    },
    {
      "type": "Screenshot",
      "url": "https://cdn1.epicgames.com/ue/product/Screenshot/Screenshot04-1920x1080-998bf291c0a35cc0398b709c70d0bebb.jpg",
      "md5": "998bf291c0a35cc0398b709c70d0bebb",
      "size": 555637,
      "uploadedDate": "2024-01-09T15:16:23.416Z",
      "width": 1920,
      "height": 1080
    },
    {
      "type": "Screenshot",
      "url": "https://cdn1.epicgames.com/ue/product/Screenshot/Screenshot05-1920x1080-ba7b808bf2b53fa27778bb5c48233a35.jpg",
      "md5": "ba7b808bf2b53fa27778bb5c48233a35",
      "size": 425582,
      "uploadedDate": "2024-01-09T15:16:24.007Z",
      "width": 1920,
      "height": 1080
    },
    {
      "type": "Screenshot",
      "url": "https://cdn1.epicgames.com/ue/product/Screenshot/Screenshot06-1920x1080-34725c4b41931bde5e3d755b3fc5163e.jpg",
      "md5": "34725c4b41931bde5e3d755b3fc5163e",
      "size": 566487,
      "uploadedDate": "2024-01-09T15:16:24.527Z",
      "width": 1920,
      "height": 1080
    },
    {
      "type": "Screenshot",
      "url": "https://cdn1.epicgames.com/ue/product/Screenshot/Screenshot07-1920x1080-e4e93cc88d617b7a38ae2f9213a586f2.jpg",
      "md5": "e4e93cc88d617b7a38ae2f9213a586f2",
      "size": 468440,
      "uploadedDate": "2024-01-09T15:16:25.096Z",
      "width": 1920,
      "height": 1080
    },
    {
      "type": "Screenshot",
      "url": "https://cdn1.epicgames.com/ue/product/Screenshot/Screenshot08-1920x1080-d5df3c7d352458d8bc1dd8948fc55d22.jpg",
      "md5": "d5df3c7d352458d8bc1dd8948fc55d22",
      "size": 583970,
      "uploadedDate": "2024-01-09T15:16:25.709Z",
      "width": 1920,
      "height": 1080
    },
    {
      "type": "Screenshot",
      "url": "https://cdn1.epicgames.com/ue/product/Screenshot/Screenshot09-1920x1080-344cb91e139aea8fa75fe8f719abb6ae.jpg",
      "md5": "344cb91e139aea8fa75fe8f719abb6ae",
      "size": 440475,
      "uploadedDate": "2024-01-09T15:16:26.513Z",
      "width": 1920,
      "height": 1080
    },
    {
      "type": "Screenshot",
      "url": "https://cdn1.epicgames.com/ue/product/Screenshot/Screenshot10-1920x1080-2f964496dd06dae9a6177c94c15b714b.jpg",
      "md5": "2f964496dd06dae9a6177c94c15b714b",
      "size": 530599,
      "uploadedDate": "2024-01-09T15:16:27.194Z",
      "width": 1920,
      "height": 1080
    },
    {
      "type": "Screenshot",
      "url": "https://cdn1.epicgames.com/ue/product/Screenshot/Screenshot11-1920x1080-73c59e2603ad516fa8e05f1a78409ff6.jpg",
      "md5": "73c59e2603ad516fa8e05f1a78409ff6",
      "size": 439292,
      "uploadedDate": "2024-01-09T15:16:27.801Z",
      "width": 1920,
      "height": 1080
    },
    {
      "type": "Screenshot",
      "url": "https://cdn1.epicgames.com/ue/product/Screenshot/Screenshot12-1920x1080-f052eb0c91765735bf0515f3c85cf3f6.jpg",
      "md5": "f052eb0c91765735bf0515f3c85cf3f6",
      "size": 516779,
      "uploadedDate": "2024-01-09T15:16:28.386Z",
      "width": 1920,
      "height": 1080
    },
    {
      "type": "Screenshot",
      "url": "https://cdn1.epicgames.com/ue/product/Screenshot/Screenshot13-1920x1080-c85226c901ec00abe333fc3c0ceb4a50.jpg",
      "md5": "c85226c901ec00abe333fc3c0ceb4a50",
      "size": 414818,
      "uploadedDate": "2024-01-09T15:16:29.011Z",
      "width": 1920,
      "height": 1080
    },
    {
      "type": "Screenshot",
      "url": "https://cdn1.epicgames.com/ue/product/Screenshot/Screenshot14-1920x1080-c37cb4a002a60d995aface64a5cd33ec.jpg",
      "md5": "c37cb4a002a60d995aface64a5cd33ec",
      "size": 575396,
      "uploadedDate": "2024-01-09T15:16:29.522Z",
      "width": 1920,
      "height": 1080
    },
    {
      "type": "Screenshot",
      "url": "https://cdn1.epicgames.com/ue/product/Screenshot/Screenshot15-1920x1080-b69f178ffe1204f885c1941971906bf3.jpg",
      "md5": "b69f178ffe1204f885c1941971906bf3",
      "size": 529062,
      "uploadedDate": "2024-01-09T15:16:30.372Z",
      "width": 1920,
      "height": 1080
    },
    {
      "type": "Screenshot",
      "url": "https://cdn1.epicgames.com/ue/product/Screenshot/Screenshot16-1920x1080-0bcc0c2ebf1cc158999d6151d2677498.jpg",
      "md5": "0bcc0c2ebf1cc158999d6151d2677498",
      "size": 559784,
      "uploadedDate": "2024-01-09T15:16:30.987Z",
      "width": 1920,
      "height": 1080
    },
    {
      "type": "Screenshot",
      "url": "https://cdn1.epicgames.com/ue/product/Screenshot/Screenshot17-1920x1080-3ad72f659fab8a9c05509b16ec85dc9f.jpg",
      "md5": "3ad72f659fab8a9c05509b16ec85dc9f",
      "size": 577618,
      "uploadedDate": "2024-01-09T15:16:31.519Z",
      "width": 1920,
      "height": 1080
    },
    {
      "type": "Screenshot",
      "url": "https://cdn1.epicgames.com/ue/product/Screenshot/Screenshot18-1920x1080-ea28ebed478c392d507d7a51ea8d18d4.jpg",
      "md5": "ea28ebed478c392d507d7a51ea8d18d4",
      "size": 676273,
      "uploadedDate": "2024-01-09T15:16:32.107Z",
      "width": 1920,
      "height": 1080
    },
    {
      "type": "Screenshot",
      "url": "https://cdn1.epicgames.com/ue/product/Screenshot/Screenshot19-1920x1080-01ff88a7069b8bd882969fbb372106c9.jpg",
      "md5": "01ff88a7069b8bd882969fbb372106c9",
      "size": 523519,
      "uploadedDate": "2024-01-09T15:16:32.730Z",
      "width": 1920,
      "height": 1080
    },
    {
      "type": "Screenshot",
      "url": "https://cdn1.epicgames.com/ue/product/Screenshot/Screenshot20-1920x1080-02378fcc58e8aa9f9a95e51750844f41.jpg",
      "md5": "02378fcc58e8aa9f9a95e51750844f41",
      "size": 644309,
      "uploadedDate": "2024-01-09T15:16:33.327Z",
      "width": 1920,
      "height": 1080
    },
    {
      "type": "Screenshot",
      "url": "https://cdn1.epicgames.com/ue/product/Screenshot/Screenshot21-1920x1080-4345a4452c37a65f3865c65157f959b2.jpg",
      "md5": "4345a4452c37a65f3865c65157f959b2",
      "size": 525782,
      "uploadedDate": "2024-01-09T15:16:33.905Z",
      "width": 1920,
      "height": 1080
    },
    {
      "type": "Screenshot",
      "url": "https://cdn1.epicgames.com/ue/product/Screenshot/Screenshot22-1920x1080-4b9c35154db03fd17c42dd246d89c3c3.jpg",
      "md5": "4b9c35154db03fd17c42dd246d89c3c3",
      "size": 562077,
      "uploadedDate": "2024-01-09T15:16:34.493Z",
      "width": 1920,
      "height": 1080
    },
    {
      "type": "Screenshot",
      "url": "https://cdn1.epicgames.com/ue/product/Screenshot/Screenshot23-1920x1080-ee499e4a5f26b3a7d6d049fa2fdabf1d.jpg",
      "md5": "ee499e4a5f26b3a7d6d049fa2fdabf1d",
      "size": 472768,
      "uploadedDate": "2024-01-09T15:16:35.058Z",
      "width": 1920,
      "height": 1080
    },
    {
      "type": "Screenshot",
      "url": "https://cdn1.epicgames.com/ue/product/Screenshot/Screenshot24-1920x1080-dfc55529b6f663c15cb2cb71a1688e61.jpg",
      "md5": "dfc55529b6f663c15cb2cb71a1688e61",
      "size": 558281,
      "uploadedDate": "2024-01-09T15:16:35.660Z",
      "width": 1920,
      "height": 1080
    },
    {
      "type": "Thumbnail",
      "url": "https://cdn1.epicgames.com/ue/product/Thumbnail/BACKGROUNDCartoonGarden2_thumb-284x284-41df280c3983226147fb4ab76d8f9b70.png",
      "md5": "41df280c3983226147fb4ab76d8f9b70",
      "size": 148273,
      "uploadedDate": "2024-01-09T15:16:36.162Z",
      "width": 284,
      "height": 284
    },
    {
      "type": "Featured",
      "url": "https://cdn1.epicgames.com/ue/product/Featured/BACKGROUNDCartoonGarden2_featured-894x488-34decaed8819e4f4e848d9f18ba79d58.png",
      "md5": "34decaed8819e4f4e848d9f18ba79d58",
      "size": 950182,
      "uploadedDate": "2024-01-09T15:16:36.337Z",
      "width": 894,
      "height": 488
    },
    {
      "type": "Snapshot",
      "url": "https://cdn1.epicgames.com/ue/product/Snapshot/Screenshot0-1920x1080-0fc545616e34c64cc4d32f6fa812ca2c_Snapshot.jpg",
      "md5": "0ee7216168aa07af0fcb6187683a1647",
      "size": 11085,
      "uploadedDate": "2024-01-09T15:16:21.298Z",
      "width": 150,
      "height": 74
    },
    {
      "type": "Snapshot",
      "url": "https://cdn1.epicgames.com/ue/product/Snapshot/Screenshot01-1920x1080-c125a078b977301085953cd9d3296a1c_Snapshot.jpg",
      "md5": "7f5ea13e3343f59de592f908385ab19e",
      "size": 8336,
      "uploadedDate": "2024-01-09T15:16:21.890Z",
      "width": 150,
      "height": 74
    },
    {
      "type": "Snapshot",
      "url": "https://cdn1.epicgames.com/ue/product/Snapshot/Screenshot02-1920x1080-7a57ba32cafa5ef2ec18e09980a94f4a_Snapshot.jpg",
      "md5": "64e18c57ebfba185ed78216285f9fde1",
      "size": 9726,
      "uploadedDate": "2024-01-09T15:16:22.531Z",
      "width": 150,
      "height": 74
    },
    {
      "type": "Snapshot",
      "url": "https://cdn1.epicgames.com/ue/product/Snapshot/Screenshot03-1920x1080-4e26cff8524d5b3a9c347bf119344af1_Snapshot.jpg",
      "md5": "994c82b985847943c42dacf37ec692d2",
      "size": 8037,
      "uploadedDate": "2024-01-09T15:16:23.245Z",
      "width": 150,
      "height": 74
    },
    {
      "type": "Snapshot",
      "url": "https://cdn1.epicgames.com/ue/product/Snapshot/Screenshot04-1920x1080-998bf291c0a35cc0398b709c70d0bebb_Snapshot.jpg",
      "md5": "1cefd2bf768d20efb0f1052915f2169d",
      "size": 9728,
      "uploadedDate": "2024-01-09T15:16:23.774Z",
      "width": 150,
      "height": 74
    },
    {
      "type": "Snapshot",
      "url": "https://cdn1.epicgames.com/ue/product/Snapshot/Screenshot05-1920x1080-ba7b808bf2b53fa27778bb5c48233a35_Snapshot.jpg",
      "md5": "c0c8c1f50a793c936bcc7faa27186878",
      "size": 8682,
      "uploadedDate": "2024-01-09T15:16:24.348Z",
      "width": 150,
      "height": 74
    },
    {
      "type": "Snapshot",
      "url": "https://cdn1.epicgames.com/ue/product/Snapshot/Screenshot06-1920x1080-34725c4b41931bde5e3d755b3fc5163e_Snapshot.jpg",
      "md5": "ef9390f5c0023a8bd31ebd8881a27ca7",
      "size": 10240,
      "uploadedDate": "2024-01-09T15:16:24.861Z",
      "width": 150,
      "height": 74
    },
    {
      "type": "Snapshot",
      "url": "https://cdn1.epicgames.com/ue/product/Snapshot/Screenshot07-1920x1080-e4e93cc88d617b7a38ae2f9213a586f2_Snapshot.jpg",
      "md5": "064d2dd08674ecccd7754c36d0d545eb",
      "size": 9153,
      "uploadedDate": "2024-01-09T15:16:25.487Z",
      "width": 150,
      "height": 74
    },
    {
      "type": "Snapshot",
      "url": "https://cdn1.epicgames.com/ue/product/Snapshot/Screenshot08-1920x1080-d5df3c7d352458d8bc1dd8948fc55d22_Snapshot.jpg",
      "md5": "8b557f8a7d3097ee4324325e2d563f42",
      "size": 10551,
      "uploadedDate": "2024-01-09T15:16:26.161Z",
      "width": 150,
      "height": 74
    },
    {
      "type": "Snapshot",
      "url": "https://cdn1.epicgames.com/ue/product/Snapshot/Screenshot09-1920x1080-344cb91e139aea8fa75fe8f719abb6ae_Snapshot.jpg",
      "md5": "c3975475b804ab4bfe8b0a4df5ed488c",
      "size": 8243,
      "uploadedDate": "2024-01-09T15:16:26.906Z",
      "width": 150,
      "height": 74
    },
    {
      "type": "Snapshot",
      "url": "https://cdn1.epicgames.com/ue/product/Snapshot/Screenshot10-1920x1080-2f964496dd06dae9a6177c94c15b714b_Snapshot.jpg",
      "md5": "530a703535d249f1ffaa4c28135460cf",
      "size": 9950,
      "uploadedDate": "2024-01-09T15:16:27.593Z",
      "width": 150,
      "height": 74
    },
    {
      "type": "Snapshot",
      "url": "https://cdn1.epicgames.com/ue/product/Snapshot/Screenshot11-1920x1080-73c59e2603ad516fa8e05f1a78409ff6_Snapshot.jpg",
      "md5": "f6290249a11e2c3a9e498e6bf0635c6e",
      "size": 8525,
      "uploadedDate": "2024-01-09T15:16:28.132Z",
      "width": 150,
      "height": 74
    },
    {
      "type": "Snapshot",
      "url": "https://cdn1.epicgames.com/ue/product/Snapshot/Screenshot12-1920x1080-f052eb0c91765735bf0515f3c85cf3f6_Snapshot.jpg",
      "md5": "ea52d191d69d5274163e36950a2e260b",
      "size": 9636,
      "uploadedDate": "2024-01-09T15:16:28.745Z",
      "width": 150,
      "height": 74
    },
    {
      "type": "Snapshot",
      "url": "https://cdn1.epicgames.com/ue/product/Snapshot/Screenshot13-1920x1080-c85226c901ec00abe333fc3c0ceb4a50_Snapshot.jpg",
      "md5": "8645eb4e9a34119b3225410f770300d7",
      "size": 8080,
      "uploadedDate": "2024-01-09T15:16:29.334Z",
      "width": 150,
      "height": 74
    },
    {
      "type": "Snapshot",
      "url": "https://cdn1.epicgames.com/ue/product/Snapshot/Screenshot14-1920x1080-c37cb4a002a60d995aface64a5cd33ec_Snapshot.jpg",
      "md5": "255df627c3562391f15e0a74b7fdffd3",
      "size": 10201,
      "uploadedDate": "2024-01-09T15:16:29.899Z",
      "width": 150,
      "height": 74
    },
    {
      "type": "Snapshot",
      "url": "https://cdn1.epicgames.com/ue/product/Snapshot/Screenshot15-1920x1080-b69f178ffe1204f885c1941971906bf3_Snapshot.jpg",
      "md5": "f06fda973eb285d2add59ebe4b44ddef",
      "size": 9482,
      "uploadedDate": "2024-01-09T15:16:30.795Z",
      "width": 150,
      "height": 74
    },
    {
      "type": "Snapshot",
      "url": "https://cdn1.epicgames.com/ue/product/Snapshot/Screenshot16-1920x1080-0bcc0c2ebf1cc158999d6151d2677498_Snapshot.jpg",
      "md5": "f18309d040b4f555461aab44fc0b4a58",
      "size": 10037,
      "uploadedDate": "2024-01-09T15:16:31.320Z",
      "width": 150,
      "height": 74
    },
    {
      "type": "Snapshot",
      "url": "https://cdn1.epicgames.com/ue/product/Snapshot/Screenshot17-1920x1080-3ad72f659fab8a9c05509b16ec85dc9f_Snapshot.jpg",
      "md5": "43e2f683ce3b866c0aef031b6708a998",
      "size": 10101,
      "uploadedDate": "2024-01-09T15:16:31.886Z",
      "width": 150,
      "height": 74
    },
    {
      "type": "Snapshot",
      "url": "https://cdn1.epicgames.com/ue/product/Snapshot/Screenshot18-1920x1080-ea28ebed478c392d507d7a51ea8d18d4_Snapshot.jpg",
      "md5": "b3b1bf672301780a5d55a1ed7876fafe",
      "size": 11071,
      "uploadedDate": "2024-01-09T15:16:32.510Z",
      "width": 150,
      "height": 74
    },
    {
      "type": "Snapshot",
      "url": "https://cdn1.epicgames.com/ue/product/Snapshot/Screenshot19-1920x1080-01ff88a7069b8bd882969fbb372106c9_Snapshot.jpg",
      "md5": "ad41ab0f114ded2df9d66fff24ad033e",
      "size": 9612,
      "uploadedDate": "2024-01-09T15:16:33.062Z",
      "width": 150,
      "height": 74
    },
    {
      "type": "Snapshot",
      "url": "https://cdn1.epicgames.com/ue/product/Snapshot/Screenshot20-1920x1080-02378fcc58e8aa9f9a95e51750844f41_Snapshot.jpg",
      "md5": "3ef41e500b345a9e6dd01fb6f61fe415",
      "size": 10844,
      "uploadedDate": "2024-01-09T15:16:33.683Z",
      "width": 150,
      "height": 74
    },
    {
      "type": "Snapshot",
      "url": "https://cdn1.epicgames.com/ue/product/Snapshot/Screenshot21-1920x1080-4345a4452c37a65f3865c65157f959b2_Snapshot.jpg",
      "md5": "5d12f6ebfcbe5324d2af310822661e35",
      "size": 8493,
      "uploadedDate": "2024-01-09T15:16:34.269Z",
      "width": 150,
      "height": 74
    },
    {
      "type": "Snapshot",
      "url": "https://cdn1.epicgames.com/ue/product/Snapshot/Screenshot22-1920x1080-4b9c35154db03fd17c42dd246d89c3c3_Snapshot.jpg",
      "md5": "d7917e9ebb0186adb7ba2c6a0bdf2cd0",
      "size": 9872,
      "uploadedDate": "2024-01-09T15:16:34.869Z",
      "width": 150,
      "height": 74
    },
    {
      "type": "Snapshot",
      "url": "https://cdn1.epicgames.com/ue/product/Snapshot/Screenshot23-1920x1080-ee499e4a5f26b3a7d6d049fa2fdabf1d_Snapshot.jpg",
      "md5": "7b6b1f0ef8cd4e9656b794b43f263070",
      "size": 8560,
      "uploadedDate": "2024-01-09T15:16:35.457Z",
      "width": 150,
      "height": 74
    },
    {
      "type": "Snapshot",
      "url": "https://cdn1.epicgames.com/ue/product/Snapshot/Screenshot24-1920x1080-dfc55529b6f663c15cb2cb71a1688e61_Snapshot.jpg",
      "md5": "2be289ac3e6df3ace9aa9ffa80905604",
      "size": 9676,
      "uploadedDate": "2024-01-09T15:16:36.108Z",
      "width": 150,
      "height": 74
    }
  ],
  "items": [
    {
      "id": "28105ff328aa4cbd90497c9f61975a3b"
    }
  ],
  "catalogNs": null
}